facedet/__init__.py
facedet/faceext.py
facedet/setup.py
facedet-2.0.dist-info/LICENSE.txt
facedet-2.0.dist-info/METADATA
facedet-2.0.dist-info/WHEEL
facedet-2.0.dist-info/top_level.txt
facedet-2.0.dist-info/RECORD
