Metadata-Version: 2.1
Name: facedet
Version: 2.0
Summary: Face extraction system
Home-page: https://github.com/Batserine/Face_extraction
Author: Balakrishna Kommanaboina
Author-email: balu636216@gmail.com
License: UNKNOWN
Platform: UNKNOWN
Classifier: Programming Language :: Python :: 3
Classifier: License :: OSI Approved :: MIT License
Classifier: Operating System :: OS Independent
